README.txt
setup.py
demo/__init__.py
demo/views.py
pyramid_signup/__init__.py
pyramid_signup/events.py
pyramid_signup/forms.py
pyramid_signup/interfaces.py
pyramid_signup/lib.py
pyramid_signup/managers.py
pyramid_signup/models.py
pyramid_signup/resources.py
pyramid_signup/routes.py
pyramid_signup/schemas.py
pyramid_signup/views.py
pyramid_signup.egg-info/PKG-INFO
pyramid_signup.egg-info/SOURCES.txt
pyramid_signup.egg-info/dependency_links.txt
pyramid_signup.egg-info/not-zip-safe
pyramid_signup.egg-info/requires.txt
pyramid_signup.egg-info/top_level.txt
pyramid_signup/scripts/__init__.py
pyramid_signup/scripts/populate.py
pyramid_signup/tests/__init__.py
pyramid_signup/tests/test_init.py
pyramid_signup/tests/test_integration.py
pyramid_signup/tests/test_interfaces.py
pyramid_signup/tests/test_lib.py
pyramid_signup/tests/test_managers.py
pyramid_signup/tests/test_models.py
pyramid_signup/tests/test_resources.py
pyramid_signup/tests/test_schemas.py
pyramid_signup/tests/test_utils.py
pyramid_signup/tests/test_views.py