Metadata-Version: 1.0
Name: pyramid-signup
Version: 0.2
Summary: Generic user registration for pyramid
Home-page: https://github.com/sontek/pyramid_signup
Author: John Anderson
Author-email: sontek@gmail.com
License: BSD
Keywords: pyramid
Platform: UNKNOWN
Classifier: Development Status :: 4 - Beta
Classifier: Environment :: Web Environment
Classifier: Intended Audience :: Developers
Classifier: License :: OSI Approved :: BSD License
Classifier: Operating System :: OS Independent
Classifier: Programming Language :: Python
Classifier: Topic :: Internet :: WWW/HTTP :: Dynamic Content
Classifier: Topic :: Software Development :: Libraries :: Python Modules
